bodhi/__init__.py
bodhi/client/__init__.py
bodhi/client/bindings.py
bodhi/messages/__init__.py
bodhi/messages/utils.py
bodhi/messages/schemas/__init__.py
bodhi/messages/schemas/base.py
bodhi/messages/schemas/buildroot_override.py
bodhi/messages/schemas/compose.py
bodhi/messages/schemas/errata.py
bodhi/messages/schemas/update.py
bodhi/server/__init__.py
bodhi/server/bugs.py
bodhi/server/buildsys.py
bodhi/server/config.py
bodhi/server/exceptions.py
bodhi/server/ffmarkdown.py
bodhi/server/logging.py
bodhi/server/mail.py
bodhi/server/metadata.py
bodhi/server/models.py
bodhi/server/notifications.py
bodhi/server/push.py
bodhi/server/renderers.py
bodhi/server/schemas.py
bodhi/server/security.py
bodhi/server/util.py
bodhi/server/validators.py
bodhi/server/webapp.py
bodhi/server/consumers/__init__.py
bodhi/server/consumers/automatic_updates.py
bodhi/server/consumers/ci.py
bodhi/server/consumers/resultsdb.py
bodhi/server/consumers/signed.py
bodhi/server/consumers/util.py
bodhi/server/consumers/waiverdb.py
bodhi/server/email/templates/fedora_epel_errata_template.tpl
bodhi/server/email/templates/fedora_epel_legacy_errata_template.tpl
bodhi/server/email/templates/fedora_errata_template.tpl
bodhi/server/email/templates/fedora_modular_errata_template.tpl
bodhi/server/email/templates/maillist_template.tpl
bodhi/server/locale/.placeholder
bodhi/server/migrations/__init__.py
bodhi/server/migrations/env.py
bodhi/server/migrations/script.py.mako
bodhi/server/migrations/versions/190ba571c7d2_remove_the_batching_request_state.py
bodhi/server/migrations/versions/19e28e9851a2_index_comment_update_id.py
bodhi/server/migrations/versions/1c97477e38ee_convert_br_override_notes_to_unicodetext.py
bodhi/server/migrations/versions/2fc96aa44a74_drop_the_user_show_popup_column.py
bodhi/server/migrations/versions/325954bac9f7_link_testcases_to_builds.py
bodhi/server/migrations/versions/3a2e248d1757_add_the_unspecified_enum_to_updatetype.py
bodhi-5.7.5.dist-info/COPYING
bodhi-5.7.5.dist-info/METADATA
bodhi-5.7.5.dist-info/WHEEL
bodhi-5.7.5.dist-info/top_level.txt
bodhi-5.7.5.dist-info/RECORD
